gbstats/__init__.py
gbstats/bayesian/__init__.py
gbstats/bayesian/dists.py
gbstats/bayesian/orthogonal.py
gbstats/bayesian/tests.py
gbstats/frequentist/__init__.py
gbstats/frequentist/tests.py
gbstats/gbstats.py
gbstats/gen_notebook.py
gbstats/messages.py
gbstats/models/results.py
gbstats/models/settings.py
gbstats/models/statistics.py
gbstats/models/tests.py
gbstats/utils.py
gbstats-0.7.0.dist-info/LICENSE
gbstats-0.7.0.dist-info/METADATA
gbstats-0.7.0.dist-info/WHEEL
gbstats-0.7.0.dist-info/RECORD
